types4yaml
