Metadata-Version: 1.0
Name: types4yaml
Version: 1.3
Summary: A basic type schema for JSON/YAML data
Home-page: UNKNOWN
Author: Thomas Conway
Author-email: drtomc@gmail.com
License: UNKNOWN
Platform: UNKNOWN
